fructose/__init__.py
fructose/ai.py
fructose/function_helpers.py
fructose/type_parser.py
fructose_ai-0.0.1.dist-info/METADATA
fructose_ai-0.0.1.dist-info/WHEEL
fructose_ai-0.0.1.dist-info/top_level.txt
fructose_ai-0.0.1.dist-info/RECORD
