Metadata-Version: 2.1
Name: fructose-ai
Version: 0.0.1
Summary: A package for strongly-typed LLM function calling
Home-page: https://github.com/bananaml/fructose
Author: Banana
Author-email: erik@banana.dev
Requires-Dist: openai
